odoo/addons/hr_employee_multidepartment/README.rst
odoo/addons/hr_employee_multidepartment/__init__.py
odoo/addons/hr_employee_multidepartment/__manifest__.py
odoo/addons/hr_employee_multidepartment/models/__init__.py
odoo/addons/hr_employee_multidepartment/models/hr_employee.py
odoo/addons/hr_employee_multidepartment/readme/DESCRIPTION.rst
odoo/addons/hr_employee_multidepartment/static/description/index.html
odoo/addons/hr_employee_multidepartment/tests/__init__.py
odoo/addons/hr_employee_multidepartment/tests/test_hr_employee_multidepartment.py
odoo/addons/hr_employee_multidepartment/views/hr_employee_views.xml
odoo/addons/hr_employee_multidepartment/views/hr_leave_views.xml
odoo12_addon_hr_employee_multidepartment-12.0.0.0.5.dist-info/METADATA
odoo12_addon_hr_employee_multidepartment-12.0.0.0.5.dist-info/WHEEL
odoo12_addon_hr_employee_multidepartment-12.0.0.0.5.dist-info/top_level.txt
odoo12_addon_hr_employee_multidepartment-12.0.0.0.5.dist-info/RECORD
