Metadata-Version: 2.1
Name: odoo12-addon-hr-employee-multidepartment
Version: 12.0.0.0.5
Summary: Add multidepartment feature.
Home-page: https://github.com/OCA/hr
Author: Som Energia SCCL, Odoo Community Association (OCA)
Author-email: support@odoo-community.org
License: AGPL-3
Platform: UNKNOWN
Classifier: Programming Language :: Python
Classifier: Framework :: Odoo
Classifier: License :: OSI Approved :: GNU Affero General Public License v3
Requires-Python: >=3.5
Requires-Dist: odoo (<12.1dev,>=12.0a)
